<?xml version="1.0" encoding="utf-8"?>
	<annotation>
		<folder>driving_annotation_dataset</folder>
		<filename>13_Interview_Interview_On_Location_13_199.jpg</filename>
		<size>
			<width>1024</width>
			<height>1024</height>
			<depth>3</depth>
		</size>
		<object>
			<name>no-mask</name>
			<pose>Unspecified</pose>
			<truncated>0</truncated>
			<difficult>0</difficult>
			<bndbox>
				<xmin>7</xmin>
				<ymin>275</ymin>
				<xmax>77</xmax>
				<ymax>397</ymax>
			</bndbox>
		</object>
		<object>
			<name>no-mask</name>
			<pose>Unspecified</pose>
			<truncated>0</truncated>
			<difficult>0</difficult>
			<bndbox>
				<xmin>253</xmin>
				<ymin>257</ymin>
				<xmax>333</xmax>
				<ymax>387</ymax>
			</bndbox>
		</object>
		<object>
			<name>no-mask</name>
			<pose>Unspecified</pose>
			<truncated>0</truncated>
			<difficult>0</difficult>
			<bndbox>
				<xmin>497</xmin>
				<ymin>259</ymin>
				<xmax>583</xmax>
				<ymax>393</ymax>
			</bndbox>
		</object>
		<object>
			<name>no-mask</name>
			<pose>Unspecified</pose>
			<truncated>0</truncated>
			<difficult>0</difficult>
			<bndbox>
				<xmin>739</xmin>
				<ymin>207</ymin>
				<xmax>835</xmax>
				<ymax>341</ymax>
			</bndbox>
		</object>
		<object>
			<name>no-mask</name>
			<pose>Unspecified</pose>
			<truncated>0</truncated>
			<difficult>0</difficult>
			<bndbox>
				<xmin>941</xmin>
				<ymin>171</ymin>
				<xmax>1023</xmax>
				<ymax>323</ymax>
			</bndbox>
		</object>
	</annotation>
