<?xml version="1.0" encoding="utf-8"?>
	<annotation>
		<folder>driving_annotation_dataset</folder>
		<filename>13_Interview_Interview_On_Location_13_240.jpg</filename>
		<size>
			<width>1024</width>
			<height>683</height>
			<depth>3</depth>
		</size>
		<object>
			<name>no-mask</name>
			<pose>Unspecified</pose>
			<truncated>0</truncated>
			<difficult>0</difficult>
			<bndbox>
				<xmin>499</xmin>
				<ymin>81</ymin>
				<xmax>567</xmax>
				<ymax>183</ymax>
			</bndbox>
		</object>
		<object>
			<name>no-mask</name>
			<pose>Unspecified</pose>
			<truncated>0</truncated>
			<difficult>0</difficult>
			<bndbox>
				<xmin>883</xmin>
				<ymin>105</ymin>
				<xmax>953</xmax>
				<ymax>225</ymax>
			</bndbox>
		</object>
		<object>
			<name>no-mask</name>
			<pose>Unspecified</pose>
			<truncated>0</truncated>
			<difficult>0</difficult>
			<bndbox>
				<xmin>211</xmin>
				<ymin>119</ymin>
				<xmax>289</xmax>
				<ymax>239</ymax>
			</bndbox>
		</object>
		<object>
			<name>no-mask</name>
			<pose>Unspecified</pose>
			<truncated>0</truncated>
			<difficult>0</difficult>
			<bndbox>
				<xmin>149</xmin>
				<ymin>227</ymin>
				<xmax>219</xmax>
				<ymax>351</ymax>
			</bndbox>
		</object>
		<object>
			<name>no-mask</name>
			<pose>Unspecified</pose>
			<truncated>0</truncated>
			<difficult>0</difficult>
			<bndbox>
				<xmin>499</xmin>
				<ymin>559</ymin>
				<xmax>579</xmax>
				<ymax>673</ymax>
			</bndbox>
		</object>
	</annotation>
