<?xml version="1.0" encoding="utf-8"?>
	<annotation>
		<folder>driving_annotation_dataset</folder>
		<filename>4_Dancing_Dancing_4_53.jpg</filename>
		<size>
			<width>1024</width>
			<height>892</height>
			<depth>3</depth>
		</size>
		<object>
			<name>no-mask</name>
			<pose>Unspecified</pose>
			<truncated>0</truncated>
			<difficult>0</difficult>
			<bndbox>
				<xmin>295</xmin>
				<ymin>205</ymin>
				<xmax>365</xmax>
				<ymax>283</ymax>
			</bndbox>
		</object>
		<object>
			<name>no-mask</name>
			<pose>Unspecified</pose>
			<truncated>0</truncated>
			<difficult>0</difficult>
			<bndbox>
				<xmin>101</xmin>
				<ymin>209</ymin>
				<xmax>183</xmax>
				<ymax>325</ymax>
			</bndbox>
		</object>
		<object>
			<name>no-mask</name>
			<pose>Unspecified</pose>
			<truncated>0</truncated>
			<difficult>0</difficult>
			<bndbox>
				<xmin>405</xmin>
				<ymin>243</ymin>
				<xmax>471</xmax>
				<ymax>325</ymax>
			</bndbox>
		</object>
		<object>
			<name>no-mask</name>
			<pose>Unspecified</pose>
			<truncated>0</truncated>
			<difficult>0</difficult>
			<bndbox>
				<xmin>577</xmin>
				<ymin>281</ymin>
				<xmax>637</xmax>
				<ymax>373</ymax>
			</bndbox>
		</object>
	</annotation>
